daimyo/__init__.py
daimyo/__main__.py
daimyo/application/__init__.py
daimyo/application/rule_service.py
daimyo/application/scope_service.py
daimyo/application/validation.py
daimyo/application/error_handling/__init__.py
daimyo/application/error_handling/error_mapper.py
daimyo/application/filtering/__init__.py
daimyo/application/filtering/category_filter.py
daimyo/application/filtering/category_parser.py
daimyo/application/formatters/__init__.py
daimyo/application/formatters/context_formatter.py
daimyo/application/formatters/index_markdown_formatter.py
daimyo/application/formatters/json_formatter.py
daimyo/application/formatters/markdown_formatter.py
daimyo/application/formatters/tree_builder.py
daimyo/application/formatters/yaml_formatter.py
daimyo/application/formatters/helpers/__init__.py
daimyo/application/formatters/helpers/dict_navigator.py
daimyo/application/formatters/helpers/metadata_builder.py
daimyo/application/formatters/helpers/rule_processor.py
daimyo/application/formatters/helpers/template_aware.py
daimyo/application/scope_resolution/__init__.py
daimyo/application/scope_resolution/circular_dependency_detector.py
daimyo/application/scope_resolution/multi_parent_resolver.py
daimyo/application/scope_resolution/parent_resolver.py
daimyo/application/scope_resolution/remote_scope_fetcher.py
daimyo/application/scope_resolution/scope_resolver.py
daimyo/application/scope_resolution/shard_merger.py
daimyo/application/templating/__init__.py
daimyo/application/templating/template_renderer.py
daimyo/config/__init__.py
daimyo/config/discovery.py
daimyo/config/settings.py
daimyo/domain/__init__.py
daimyo/domain/exceptions.py
daimyo/domain/models.py
daimyo/domain/protocols.py
daimyo/infrastructure/__init__.py
daimyo/infrastructure/composite/__init__.py
daimyo/infrastructure/composite/composite_repository.py
daimyo/infrastructure/di/__init__.py
daimyo/infrastructure/di/container.py
daimyo/infrastructure/filesystem/__init__.py
daimyo-1.11.0.dist-info/METADATA
daimyo-1.11.0.dist-info/WHEEL
daimyo-1.11.0.dist-info/entry_points.txt
daimyo-1.11.0.dist-info/licenses/LICENSE
daimyo-1.11.0.dist-info/RECORD
