Metadata-Version: 2.4
Name: daimyo
Version: 1.11.0
Summary: Rules server for agents with REST and MCP interfaces
Project-URL: Homepage, https://gitlab.com/Kencho1/daimyo
Project-URL: Repository, https://gitlab.com/Kencho1/daimyo
Project-URL: Issues, https://gitlab.com/Kencho1/daimyo/-/issues
Project-URL: Changelog, https://gitlab.com/Kencho1/daimyo/-/blob/main/CHANGELOG.md
Author: Jesús Alonso Abad
License: MIT
License-File: LICENSE
Classifier: Development Status :: 5 - Production/Stable
Classifier: Intended Audience :: Developers
Classifier: License :: OSI Approved :: MIT License
Classifier: Programming Language :: Python :: 3
Classifier: Programming Language :: Python :: 3.11
Classifier: Programming Language :: Python :: 3.12
Classifier: Programming Language :: Python :: 3.13
Classifier: Programming Language :: Python :: 3.14
Requires-Python: >=3.11
Requires-Dist: cachetools~=5.3
Requires-Dist: dynaconf~=3.2
Requires-Dist: fastapi~=0.127
Requires-Dist: fastmcp~=2.14
Requires-Dist: httpx~=0.28
Requires-Dist: jinja2~=3.1
Requires-Dist: loguru~=0.7
Requires-Dist: pydantic~=2.10
Requires-Dist: pyyaml~=6.0
Requires-Dist: typer~=0.15
Requires-Dist: uvicorn[standard]~=0.32
Provides-Extra: dev
Requires-Dist: mypy~=1.13; extra == 'dev'
Requires-Dist: pytest-asyncio~=0.24; extra == 'dev'
Requires-Dist: pytest-cov~=6.0; extra == 'dev'
Requires-Dist: pytest-httpx~=0.35; extra == 'dev'
Requires-Dist: pytest~=8.3; extra == 'dev'
Requires-Dist: ruff~=0.8; extra == 'dev'
